{
  "arxiv_id": "2602.13697",
  "title": "No Need to Train Your RDB Foundation Model",
  "abstract": "Relational databases (RDBs) contain vast amounts of heterogeneous tabular information that can be exploited for predictive modeling purposes. But since the space of potential targets is vast across enterprise settings, how can we avoid retraining a new model each time we wish to predict a new quantity of interest? Foundation models based on in-context learning (ICL) offer a convenient option, but so far are largely restricted to single-table operability. In generalizing to multiple interrelated tables, it is essential to compress variably-sized RDB neighborhoods into fixed-length ICL samples for consumption by the decoder. However, the details here are critical: unlike existing supervised learning RDB pipelines, we provide theoretical and empirical evidence that ICL-specific compression should be constrained within high-dimensional RDB columns where all entities share units and roles, not across columns where the relevance of heterogeneous data types cannot be determined without extensive label information. Conditioned on this restriction, we then demonstrate that encoder expressiveness is actually not compromised by excluding trainable parameters. Hence we arrive at a principled family of RDB encoders that can be seamlessly paired with already-existing single-table ICL foundation models, whereby no training or fine-tuning is required. From a practical standpoint, we develop scalable SQL primitives to implement the encoder stage, resulting in the easy-to-use open-source RDBLearn foundation model capable of robust performance on unseen datasets out of the box.",
  "link": "https://arxiv.org/abs/2602.13697",
  "category": "cs.LG",
  "categories": [
    "cs.AI",
    "cs.DB",
    "cs.LG"
  ],
  "pulled_at": "2026-06-05T08:23:10.884611+00:00"
}