{
  "arxiv_id": "2605.31277",
  "title": "GETA: Generalized Encrypted Traffic Analysis",
  "abstract": "Traditional traffic analysis is being fundamentally challenged by the rapid adoption of encryption, tunnelling, and privacy-preserving protocols, which increasingly obscure packet payloads and limit the usefulness of Deep Packet Inspection (DPI). Although machine learning has advanced encrypted traffic analysis, existing approaches often remain tied to protocol-specific header features, depend on large labelled datasets, and degrade when deployed across heterogeneous network environments. We present GETA, a protocol-agnostic framework for encrypted traffic analysis that models network flows as multivariate time series using only traffic metadata, thereby avoiding reliance on packet payloads or header semantics. GETA combines meta-learning, embedding refinement, and self-attention to support few-shot adaptation to previously unseen domains with minimal labelled data. Across nine public datasets spanning application identification, VPN traffic classification, IoT device fingerprinting, and attack detection, GETA consistently outperforms state-of-the-art baselines. These results show that GETA offers a practical and generalisable foundation for robust traffic analysis in modern encrypted networks.",
  "link": "https://arxiv.org/abs/2605.31277",
  "category": "cs.LG",
  "categories": [
    "cs.CR",
    "cs.LG"
  ],
  "pulled_at": "2026-06-01T19:47:28.307485Z"
}